odoo/addons/account_invoice_customer_no_autofollow/README.rst
odoo/addons/account_invoice_customer_no_autofollow/__init__.py
odoo/addons/account_invoice_customer_no_autofollow/__manifest__.py
odoo/addons/account_invoice_customer_no_autofollow/i18n/account_invoice_customer_no_autofollow.pot
odoo/addons/account_invoice_customer_no_autofollow/i18n/it.po
odoo/addons/account_invoice_customer_no_autofollow/models/__init__.py
odoo/addons/account_invoice_customer_no_autofollow/models/account_move.py
odoo/addons/account_invoice_customer_no_autofollow/models/res_config_settings.py
odoo/addons/account_invoice_customer_no_autofollow/readme/CONFIGURE.md
odoo/addons/account_invoice_customer_no_autofollow/readme/CONTRIBUTORS.md
odoo/addons/account_invoice_customer_no_autofollow/readme/DESCRIPTION.md
odoo/addons/account_invoice_customer_no_autofollow/static/description/icon.png
odoo/addons/account_invoice_customer_no_autofollow/static/description/index.html
odoo/addons/account_invoice_customer_no_autofollow/tests/__init__.py
odoo/addons/account_invoice_customer_no_autofollow/tests/common.py
odoo/addons/account_invoice_customer_no_autofollow/tests/test_no_autofollow_disabled.py
odoo/addons/account_invoice_customer_no_autofollow/tests/test_no_autofollow_enabled.py
odoo/addons/account_invoice_customer_no_autofollow/views/res_config_settings.xml
odoo_addon_account_invoice_customer_no_autofollow-17.0.1.0.0.4.dist-info/METADATA
odoo_addon_account_invoice_customer_no_autofollow-17.0.1.0.0.4.dist-info/WHEEL
odoo_addon_account_invoice_customer_no_autofollow-17.0.1.0.0.4.dist-info/top_level.txt
odoo_addon_account_invoice_customer_no_autofollow-17.0.1.0.0.4.dist-info/RECORD
